{
  "id": "github:HKUDS/DeepTutor",
  "name": "DeepTutor",
  "description": "DeepTutor: Lifelong Personalized Tutoring. https://deeptutor.info/ .",
  "quadrant": "Languages",
  "ring": "Discovered",
  "source": "GitHub",
  "discovered_by": "scraper",
  "url": "https://github.com/HKUDS/DeepTutor",
  "canonical_url": "github.com/hkuds/deeptutor",
  "also_seen": [],
  "company": null,
  "stars": 172,
  "momentum": 17,
  "tags": [
    "python"
  ],
  "topics": [],
  "archived_at": null,
  "first_seen": "2026-07-16",
  "last_seen": "2026-07-16",
  "stars_history": {
    "2026-07-16": 172
  }
}