{
  "id": "github:k1tbyte/Wand-Enhancer",
  "name": "Wand-Enhancer",
  "description": "Advanced UX and interoperability extension for Wand (WeMod) app",
  "quadrant": "Tools",
  "ring": "Discovered",
  "source": "GitHub",
  "discovered_by": "scraper",
  "url": "https://github.com/k1tbyte/Wand-Enhancer",
  "canonical_url": "github.com/k1tbyte/wand-enhancer",
  "also_seen": [],
  "company": null,
  "stars": 609,
  "momentum": 60,
  "tags": [
    "c#"
  ],
  "topics": [],
  "archived_at": null,
  "first_seen": "2026-07-13",
  "last_seen": "2026-07-13",
  "stars_history": {
    "2026-07-13": 609
  }
}